tick_data_downloader/__init__.py
tick_data_downloader/date_picker.py
tick_data_downloader/downloader.py
tick_data_downloader/main_downloader.py
tick_data_downloader/symbol_picker.py
tick_data_downloader/tz.py
tick_sponge-0.1.1.dist-info/licenses/LICENSE
tick_sponge-0.1.1.dist-info/METADATA
tick_sponge-0.1.1.dist-info/WHEEL
tick_sponge-0.1.1.dist-info/top_level.txt
tick_sponge-0.1.1.dist-info/RECORD
